phishsage/__init__.py
phishsage/main.py
phishsage/config/__init__.py
phishsage/config/config.toml
phishsage/config/loader.py
phishsage/heuristics/__init__.py
phishsage/heuristics/headers.py
phishsage/heuristics/links.py
phishsage/utils/__init__.py
phishsage/utils/api_clients.py
phishsage/utils/attachments.py
phishsage/utils/cli_args.py
phishsage/utils/dirty_parser.py
phishsage/utils/header_helpers.py
phishsage/utils/header_parser.py
phishsage/utils/ip_analysis.py
phishsage/utils/url_helpers.py
phishsage-1.1.0.dist-info/licenses/LICENSE
phishsage-1.1.0.dist-info/METADATA
phishsage-1.1.0.dist-info/WHEEL
phishsage-1.1.0.dist-info/entry_points.txt
phishsage-1.1.0.dist-info/top_level.txt
phishsage-1.1.0.dist-info/RECORD
