Metadata-Version: 2.4
Name: phishsage
Version: 1.1.0
Summary: Lightweight email triage and phishing-analysis toolkit. Extracts headers, attachments, and links, applies heuristic checks, and produces structured insights.
Author-email: Adams <208283706+0xlam@users.noreply.github.com>
License-Expression: MIT
Project-URL: Homepage, https://github.com/0xlam/PhishSage
Project-URL: Repository, https://github.com/0xlam/PhishSage
Project-URL: Issues, https://github.com/0xlam/PhishSage/issues
Keywords: phishing,email-security,SOC,SIEM,threat-intelligence,email-analysis,cybersecurity,phish-detection,incident-response
Classifier: Development Status :: 4 - Beta
Classifier: Intended Audience :: System Administrators
Classifier: Programming Language :: Python
Classifier: Programming Language :: Python :: 3
Classifier: Programming Language :: Python :: 3.9
Classifier: Programming Language :: Python :: 3.10
Classifier: Programming Language :: Python :: 3.11
Classifier: Topic :: Security
Requires-Python: >=3.9
License-File: LICENSE
Requires-Dist: beautifulsoup4==4.13.5
Requires-Dist: certifi==2025.10.5
Requires-Dist: cffi==2.0.0
Requires-Dist: charset-normalizer==3.4.4
Requires-Dist: cryptography==43.0.0
Requires-Dist: dnspython==2.8.0
Requires-Dist: email_validator==2.2.0
Requires-Dist: filelock==3.20.0
Requires-Dist: idna==3.10
Requires-Dist: mail-parser==4.1.4
Requires-Dist: pycparser==2.23
Requires-Dist: pycryptodomex==3.20.0
Requires-Dist: python-dateutil==2.9.0.post0
Requires-Dist: python-dotenv==1.1.1
Requires-Dist: python-magic==0.4.27
Requires-Dist: python-whois==0.9.3
Requires-Dist: requests==2.32.4
Requires-Dist: requests-file==3.0.1
Requires-Dist: six==1.17.0
Requires-Dist: soupsieve==2.8
Requires-Dist: tldextract==5.3.0
Requires-Dist: typing_extensions==4.15.0
Requires-Dist: urllib3==2.5.0
Requires-Dist: vt-py==0.22.0
Requires-Dist: yara-python==4.5.4
Dynamic: license-file
